charentais/__init__.py
charentais/architecture.s.HTML
charentais/module.MD
charentais/module.s.HTML
charentais/__agenda/maybes.s.HTML
charentais/__agenda/priorities.s.HTML
charentais/__agenda/processes/errout/script.py
charentais/__agenda/processes/errout/start.py
charentais/__agenda/processes/errout_v1/script.py
charentais/__agenda/processes/errout_v1/start.py
charentais/__agenda/processes/errout_v2/script.py
charentais/__agenda/processes/errout_v2/start.py
charentais/__license/license.s.HTML
charentais/_book/advanced tutorial.s.HTML
charentais/_book/book.s.HTML
charentais/_book/example output.s.HTML
charentais/_book/relevant.s.HTML
charentais/_clique/__init__.py
charentais/_clique/group/__init__.py
charentais/_status/establish.py
charentais/_status/status.proc.py
charentais/_status/status.s.HTML
charentais/_status/status_py.py
charentais/_status/DB/records.json
charentais/_status/monitors/-1_start/status_1.py
charentais/_status/monitors/-1_start/chassis/modules/monitor_1.py
charentais/_status/monitors/0_start/status_1.py
charentais/_status/monitors/0_start/chassis/modules/monitor_1.py
charentais/_status/monitors/1/status_1.py
charentais/_status/monitors/1/stasis/path_1_health.py
charentais/_status/monitors/1/stasis/path_2_health.py
charentais/_status/monitors/2/status_1.py
charentais/_status/monitors/2/stasis/1_health.py
charentais/_status/monitors/2/stasis/2_health.py
charentais/_status/monitors/2/stasis/modules/MODULE_1.py
charentais/_status/monitors/3_empty_glob/status_1.py
charentais/_status/monitors/4_bad_import/status_1.py
charentais/_status/monitors/4_bad_import/stasis/1_health.py
charentais/_status/monitors/5__file__/status_1.py
charentais/_status/monitors/5__file__/stasis/1_health.py
charentais/_status/monitors/5__file__/stasis/MODULES/MODULE_1.py
charentais/_status/monitors/6_various/status_1.py
charentais/_status/monitors/6_various/stasis/1_health.py
charentais/_status/monitors/6_various/stasis/2_health.py
charentais-1.0.6.dist-info/METADATA
charentais-1.0.6.dist-info/WHEEL
charentais-1.0.6.dist-info/entry_points.txt
charentais-1.0.6.dist-info/top_level.txt
charentais-1.0.6.dist-info/RECORD
