Metadata-Version: 2.1
Name: charentais
Version: 1.0.6
Summary: health checks module
License: GPL 3.0
Project-URL: GitLab, https://gitlab.com/offline-money/squash-1/charentais
Keywords: homeostasis,reliability,consistency,integrity,guarantees,vows,oaths,assurances,insurances,ensurances,speed,calmness,education,augmentation,enhancement,improvements
Requires-Python: >=3.8
Requires-Dist: body-scan
Requires-Dist: botanist
Requires-Dist: shares
Requires-Dist: click
Requires-Dist: flask
Requires-Dist: pdoc3
Requires-Dist: requests
Requires-Dist: textual
Requires-Dist: tinydb
